eaasy/__init__.py
eaasy/eaasy.py
eaasy/api/__init__.py
eaasy/api/liveness.py
eaasy/domain/__init__.py
eaasy/domain/database.py
eaasy/domain/exceptions.py
eaasy/extensions/__init__.py
eaasy/extensions/builder.py
eaasy/extensions/helper.py
eaasy/extensions/migration.py
eaasy-0.3.0.dist-info/METADATA
eaasy-0.3.0.dist-info/WHEEL
eaasy-0.3.0.dist-info/top_level.txt
eaasy-0.3.0.dist-info/RECORD
