Metadata-Version: 2.4
Name: eaasy
Version: 0.3.0
Summary: Build your e-commerce ea(a)sily
Home-page: https://github.com/ciulene/eaasy
Author: Giuliano Errico
Author-email: errgioul2@gmail.com
Classifier: Programming Language :: Python :: 3
Classifier: License :: OSI Approved :: MIT License
Classifier: Operating System :: OS Independent
Requires-Python: >=3.6
Requires-Dist: alembic==1.17.2
Requires-Dist: aniso8601==10.0.1
Requires-Dist: attrs==25.4.0
Requires-Dist: Authlib==1.6.6
Requires-Dist: blinker==1.9.0
Requires-Dist: certifi==2025.11.12
Requires-Dist: cffi==2.0.0
Requires-Dist: charset-normalizer==3.4.4
Requires-Dist: click==8.3.1
Requires-Dist: cryptography==46.0.3
Requires-Dist: Deprecated==1.3.1
Requires-Dist: et_xmlfile==2.0.0
Requires-Dist: Flask==3.1.2
Requires-Dist: flask-cors==6.0.2
Requires-Dist: Flask-Limiter==4.1.1
Requires-Dist: flask-oidc==2.4.0
Requires-Dist: flask-restx==1.3.2
Requires-Dist: greenlet==3.3.0
Requires-Dist: gunicorn==23.0.0
Requires-Dist: idna==3.11
Requires-Dist: importlib_resources==6.5.2
Requires-Dist: itsdangerous==2.2.0
Requires-Dist: Jinja2==3.1.6
Requires-Dist: jsonschema==4.25.1
Requires-Dist: jsonschema-specifications==2025.9.1
Requires-Dist: limits==5.6.0
Requires-Dist: Mako==1.3.10
Requires-Dist: markdown-it-py==4.0.0
Requires-Dist: MarkupSafe==3.0.3
Requires-Dist: mdurl==0.1.2
Requires-Dist: openpyxl==3.1.5
Requires-Dist: ordered-set==4.1.0
Requires-Dist: packaging==25.0
Requires-Dist: psycopg2-binary==2.9.11
Requires-Dist: pycparser==2.23
Requires-Dist: Pygments==2.19.2
Requires-Dist: pytz==2025.2
Requires-Dist: redis==7.1.0
Requires-Dist: referencing==0.37.0
Requires-Dist: requests==2.32.5
Requires-Dist: rich==14.2.0
Requires-Dist: rpds-py==0.30.0
Requires-Dist: SQLAlchemy==2.0.45
Requires-Dist: typing_extensions==4.15.0
Requires-Dist: urllib3==2.6.2
Requires-Dist: Werkzeug==3.1.4
Requires-Dist: wrapt==2.0.1
Dynamic: author
Dynamic: author-email
Dynamic: classifier
Dynamic: description
Dynamic: description-content-type
Dynamic: home-page
Dynamic: requires-dist
Dynamic: requires-python
Dynamic: summary
